team_classifier_osnet/__init__.py
team_classifier_osnet/main.py
team_classifier_osnet/module.pyc
team_classifier_osnet/osnet_ain.pyc
team_classifier_osnet/__pycache__/__init__.cpython-312.pyc
team_classifier_osnet/__pycache__/main.cpython-312.pyc
team_classifier_osnet-0.1.3.dist-info/licenses/LICENSE
team_classifier_osnet-0.1.3.dist-info/METADATA
team_classifier_osnet-0.1.3.dist-info/WHEEL
team_classifier_osnet-0.1.3.dist-info/top_level.txt
team_classifier_osnet-0.1.3.dist-info/RECORD
