Metadata-Version: 2.4
Name: team-classifier-osnet
Version: 0.1.3
Summary: Team Classifier OSNet package
Author-email: Colin <colin@tonvault.co>
License-Expression: MIT
Project-URL: Homepage, https://github.com/yourusername/team-classifier-osnet
Project-URL: Repository, https://github.com/yourusername/team-classifier-osnet
Keywords: classifier,osnet,team
Classifier: Development Status :: 4 - Beta
Classifier: Intended Audience :: Developers
Classifier: Programming Language :: Python :: 3
Classifier: Programming Language :: Python :: 3.7
Classifier: Programming Language :: Python :: 3.8
Classifier: Programming Language :: Python :: 3.9
Classifier: Programming Language :: Python :: 3.10
Classifier: Programming Language :: Python :: 3.11
Requires-Python: >=3.7
License-File: LICENSE
Dynamic: license-file
